arclet/alconna/avilla/__init__.py
arclet/alconna/avilla/alc.py
arclet/alconna/avilla/argv.py
arclet/alconna/avilla/create.py
arclet/alconna/avilla/dispatcher.py
arclet/alconna/avilla/i18n/.config.json
arclet/alconna/avilla/i18n/.lang.schema.json
arclet/alconna/avilla/i18n/.template.json
arclet/alconna/avilla/i18n/.template.schema.json
arclet/alconna/avilla/i18n/__init__.py
arclet/alconna/avilla/i18n/en-US.json
arclet/alconna/avilla/i18n/model.py
arclet/alconna/avilla/i18n/zh-CN.json
arclet/alconna/avilla/model.py
arclet/alconna/avilla/saya.py
arclet/alconna/avilla/tools.py
arclet/alconna/avilla/typings.py
arclet_alconna_avilla-0.19.4.dist-info/METADATA
arclet_alconna_avilla-0.19.4.dist-info/WHEEL
arclet_alconna_avilla-0.19.4.dist-info/entry_points.txt
arclet_alconna_avilla-0.19.4.dist-info/licenses/LICENSE
arclet_alconna_avilla-0.19.4.dist-info/RECORD
