Metadata-Version: 2.1
Name: arclet-alconna-avilla
Version: 0.19.4
Summary: Support Alconna for GraiaProject/Avilla
Author-Email: RF-Tar-Railt <rf_tar_railt@qq.com>
License: AGPL-3.0
Requires-Python: >=3.9
Requires-Dist: arclet-alconna<2.0.0,>=1.8.12
Requires-Dist: arclet-alconna-tools<0.8.0,>=0.7.4
Requires-Dist: tarina<0.7.0,>=0.6.8
Requires-Dist: nepattern<0.8.0,>=0.7.3
Requires-Dist: graia-amnesia>=0.5.0
Requires-Dist: graia-broadcast>=0.18.2
Requires-Dist: graia-saya>=0.0.17
Requires-Dist: avilla-core>=1.0.0a20
Requires-Dist: launart>=0.5.0
Requires-Dist: creart>=0.3.0
